genbase_test_helpers/__init__.py
genbase_test_helpers-0.1.1.dist-info/METADATA
genbase_test_helpers-0.1.1.dist-info/WHEEL
genbase_test_helpers-0.1.1.dist-info/top_level.txt
genbase_test_helpers-0.1.1.dist-info/RECORD
