Metadata-Version: 2.1
Name: genbase-test-helpers
Version: 0.1.1
Summary: Genbase generic test helpers
Home-page: UNKNOWN
Author: Marcel Robeer
License: UNKNOWN
Platform: UNKNOWN
Requires-Dist: instancelib (>=0.4.4.1)
